{
  "$schema": "https://schema.management.azure.com/schemas/2015-01-01/deploymentParameters.json#",
  "contentVersion": "1.0.0.0",
  "parameters": {
    "location": {
      "value": "eastus"
    },
    "PAppserviceName": {
      "value": "azbicep-dev-eus-asp1"
    },
    "PAppservice": {
      "value": "azbicep-dev-eus-wappp1"
    },
    "PAppinsights": {
      "value": "azbicep-dev-eus-wapp1-ai"
    },
    "PSQLServer": {
      "value": "azbicep-dev-eus-sqlserver1"
    },
    "padministratorLogin": {
      "value": "Sqladmin"
    },
    "padministratorpassword": {
      "value": ""
     }
   }
  }

